exerpy/__init__.py
exerpy/analyses.py
exerpy/functions.py
exerpy/components/__init__.py
exerpy/components/component.py
exerpy/components/combustion/__init__.py
exerpy/components/combustion/base.py
exerpy/components/heat_exchanger/__init__.py
exerpy/components/heat_exchanger/base.py
exerpy/components/heat_exchanger/condenser.py
exerpy/components/heat_exchanger/simple.py
exerpy/components/heat_exchanger/steam_generator.py
exerpy/components/helpers/__init__.py
exerpy/components/helpers/cycle_closer.py
exerpy/components/nodes/__init__.py
exerpy/components/nodes/deaerator.py
exerpy/components/nodes/drum.py
exerpy/components/nodes/flash_tank.py
exerpy/components/nodes/mixer.py
exerpy/components/piping/__init__.py
exerpy/components/piping/valve.py
exerpy/components/power_machines/__init__.py
exerpy/components/power_machines/generator.py
exerpy/components/power_machines/motor.py
exerpy/components/turbomachinery/__init__.py
exerpy/components/turbomachinery/compressor.py
exerpy/components/turbomachinery/pump.py
exerpy/components/turbomachinery/turbine.py
exerpy/data/Ahrendts.json
exerpy/parser/__init__.py
exerpy/parser/from_aspen/__init__.py
exerpy/parser/from_aspen/aspen_config.py
exerpy/parser/from_aspen/aspen_parser.py
exerpy/parser/from_ebsilon/__init__.py
exerpy/parser/from_ebsilon/check_ebs_path.py
exerpy/parser/from_ebsilon/ebsilon_config.py
exerpy/parser/from_ebsilon/ebsilon_functions.py
exerpy/parser/from_ebsilon/ebsilon_parser.py
exerpy/parser/from_ebsilon/utils.py
exerpy/parser/from_tespy/tespy_config.py
exerpy-0.0.2.dist-info/licenses/LICENSE
exerpy-0.0.2.dist-info/WHEEL
exerpy-0.0.2.dist-info/METADATA
exerpy-0.0.2.dist-info/RECORD
