Metadata-Version: 2.4
Name: exerpy
Version: 0.0.2
Summary: Exergy analysis for tabular input data
Author-email: Sergio Tomasinelli <s.tomasinelli@tu-berlin.de>, Robert Müller <robert.mueller.2@tu-berlin.de>, Francesco Witte <github@witte.sh>
Requires-Python: >=3.10
Classifier: Development Status :: 4 - Beta
Classifier: Intended Audience :: Developers
Classifier: Intended Audience :: Science/Research
Classifier: License :: OSI Approved :: MIT License
Classifier: Operating System :: Unix
Classifier: Operating System :: POSIX
Classifier: Operating System :: Microsoft :: Windows
Classifier: Operating System :: MacOS
Classifier: Operating System :: OS Independent
Classifier: Programming Language :: Python
Classifier: Programming Language :: Python :: 3
Classifier: Programming Language :: Python :: 3.10
Classifier: Programming Language :: Python :: 3.11
Classifier: Programming Language :: Python :: Implementation :: CPython
Classifier: Topic :: Utilities
License-File: LICENSE
Requires-Dist: pandas
Requires-Dist: numpy
Requires-Dist: pywin32 ; extra == "aspen"
Requires-Dist: build ; extra == "dev"
Requires-Dist: flit ; extra == "dev"
Requires-Dist: furo ; extra == "dev"
Requires-Dist: isort ; extra == "dev"
Requires-Dist: pytest ; extra == "dev"
Requires-Dist: sphinx>=7.2.2 ; extra == "dev"
Requires-Dist: sphinx-copybutton ; extra == "dev"
Requires-Dist: sphinx-design ; extra == "dev"
Requires-Dist: sphinxcontrib.bibtex ; extra == "dev"
Requires-Dist: tespy>=0.9 ; extra == "dev"
Requires-Dist: tox ; extra == "dev"
Requires-Dist: pywin32 ; extra == "ebsilon"
Requires-Dist: tespy>=0.9 ; extra == "tespy"
Project-URL: Changelog, https://exerpy.readthedocs.io/en/latest/whats_new.html
Project-URL: Documentation, https://exerpy.readthedocs.io/
Project-URL: Homepage, https://github.com/oemof/exerpy
Project-URL: Issue Tracker, https://github.com/oemof/exerpy/issues
Provides-Extra: aspen
Provides-Extra: dev
Provides-Extra: ebsilon
Provides-Extra: tespy
